{
  "generated_at": "2026-01-25T23:29:05.597582+00:00",
  "prices_used": {},
  "selected_algorithm": "Event-Driven Strategies",
  "algorithm_leaderboard": [],
  "winner_target_allocations": {},
  "winner_top_coin_scores": [],
  "main": {
    "value": 0.825,
    "cash": 0.825,
    "holdings": {},
    "pnl": -999.175,
    "pnl_pct": -99.9175,
    "total_trades": 3,
    "tax_paid": 1.994361
  },
  "actions_this_run": [],
  "equity_history": [
    {
      "ts": "2026-01-24T23:41:10.133735+00:00",
      "value": 0.825,
      "cash": 0.825
    },
    {
      "ts": "2026-01-24T23:52:47.131925+00:00",
      "value": 0.825,
      "cash": 0.825
    },
    {
      "ts": "2026-01-25T01:24:26.122059+00:00",
      "value": 0.825,
      "cash": 0.825
    },
    {
      "ts": "2026-01-25T03:28:28.261330+00:00",
      "value": 0.825,
      "cash": 0.825
    },
    {
      "ts": "2026-01-25T04:38:49.301929+00:00",
      "value": 0.825,
      "cash": 0.825
    },
    {
      "ts": "2026-01-25T05:17:14.530916+00:00",
      "value": 0.825,
      "cash": 0.825
    },
    {
      "ts": "2026-01-25T05:46:36.007656+00:00",
      "value": 0.825,
      "cash": 0.825
    },
    {
      "ts": "2026-01-25T05:59:11.436354+00:00",
      "value": 0.825,
      "cash": 0.825
    },
    {
      "ts": "2026-01-25T06:45:40.127373+00:00",
      "value": 0.825,
      "cash": 0.825
    },
    {
      "ts": "2026-01-25T07:02:10.956368+00:00",
      "value": 0.825,
      "cash": 0.825
    },
    {
      "ts": "2026-01-25T07:31:29.127246+00:00",
      "value": 0.825,
      "cash": 0.825
    },
    {
      "ts": "2026-01-25T07:46:08.597932+00:00",
      "value": 0.825,
      "cash": 0.825
    },
    {
      "ts": "2026-01-25T07:57:20.292893+00:00",
      "value": 0.825,
      "cash": 0.825
    },
    {
      "ts": "2026-01-25T08:35:56.320800+00:00",
      "value": 0.825,
      "cash": 0.825
    },
    {
      "ts": "2026-01-25T08:55:19.904584+00:00",
      "value": 0.825,
      "cash": 0.825
    },
    {
      "ts": "2026-01-25T09:24:21.120278+00:00",
      "value": 0.825,
      "cash": 0.825
    },
    {
      "ts": "2026-01-25T09:43:25.254933+00:00",
      "value": 0.825,
      "cash": 0.825
    },
    {
      "ts": "2026-01-25T09:54:59.571888+00:00",
      "value": 0.825,
      "cash": 0.825
    },
    {
      "ts": "2026-01-25T10:23:16.743189+00:00",
      "value": 0.825,
      "cash": 0.825
    },
    {
      "ts": "2026-01-25T10:44:49.198861+00:00",
      "value": 0.825,
      "cash": 0.825
    },
    {
      "ts": "2026-01-25T10:56:37.977542+00:00",
      "value": 0.825,
      "cash": 0.825
    },
    {
      "ts": "2026-01-25T11:22:18.859250+00:00",
      "value": 0.825,
      "cash": 0.825
    },
    {
      "ts": "2026-01-25T11:37:25.302934+00:00",
      "value": 0.825,
      "cash": 0.825
    },
    {
      "ts": "2026-01-25T11:48:39.699010+00:00",
      "value": 0.825,
      "cash": 0.825
    },
    {
      "ts": "2026-01-25T11:59:50.666793+00:00",
      "value": 0.825,
      "cash": 0.825
    },
    {
      "ts": "2026-01-25T13:00:34.764293+00:00",
      "value": 0.825,
      "cash": 0.825
    },
    {
      "ts": "2026-01-25T13:39:19.686807+00:00",
      "value": 0.825,
      "cash": 0.825
    },
    {
      "ts": "2026-01-25T13:54:41.222923+00:00",
      "value": 0.825,
      "cash": 0.825
    },
    {
      "ts": "2026-01-25T14:19:24.067423+00:00",
      "value": 0.825,
      "cash": 0.825
    },
    {
      "ts": "2026-01-25T14:40:40.847768+00:00",
      "value": 0.825,
      "cash": 0.825
    },
    {
      "ts": "2026-01-25T14:53:02.515839+00:00",
      "value": 0.825,
      "cash": 0.825
    },
    {
      "ts": "2026-01-25T15:16:31.853521+00:00",
      "value": 0.825,
      "cash": 0.825
    },
    {
      "ts": "2026-01-25T15:37:24.734224+00:00",
      "value": 0.825,
      "cash": 0.825
    },
    {
      "ts": "2026-01-25T15:50:50.368878+00:00",
      "value": 0.825,
      "cash": 0.825
    },
    {
      "ts": "2026-01-25T16:13:49.355990+00:00",
      "value": 0.825,
      "cash": 0.825
    },
    {
      "ts": "2026-01-25T16:44:39.578209+00:00",
      "value": 0.825,
      "cash": 0.825
    },
    {
      "ts": "2026-01-25T16:59:02.382594+00:00",
      "value": 0.825,
      "cash": 0.825
    },
    {
      "ts": "2026-01-25T17:27:14.666568+00:00",
      "value": 0.825,
      "cash": 0.825
    },
    {
      "ts": "2026-01-25T17:44:47.488122+00:00",
      "value": 0.825,
      "cash": 0.825
    },
    {
      "ts": "2026-01-25T17:55:51.315786+00:00",
      "value": 0.825,
      "cash": 0.825
    },
    {
      "ts": "2026-01-25T18:34:35.304363+00:00",
      "value": 0.825,
      "cash": 0.825
    },
    {
      "ts": "2026-01-25T18:56:23.217220+00:00",
      "value": 0.825,
      "cash": 0.825
    },
    {
      "ts": "2026-01-25T19:20:47.182918+00:00",
      "value": 0.825,
      "cash": 0.825
    },
    {
      "ts": "2026-01-25T19:34:14.090761+00:00",
      "value": 0.825,
      "cash": 0.825
    },
    {
      "ts": "2026-01-25T19:45:55.939483+00:00",
      "value": 0.825,
      "cash": 0.825
    },
    {
      "ts": "2026-01-25T19:57:14.986425+00:00",
      "value": 0.825,
      "cash": 0.825
    },
    {
      "ts": "2026-01-25T20:31:57.606594+00:00",
      "value": 0.825,
      "cash": 0.825
    },
    {
      "ts": "2026-01-25T20:50:02.795327+00:00",
      "value": 0.825,
      "cash": 0.825
    },
    {
      "ts": "2026-01-25T21:08:31.227615+00:00",
      "value": 0.825,
      "cash": 0.825
    },
    {
      "ts": "2026-01-25T21:31:14.564709+00:00",
      "value": 0.825,
      "cash": 0.825
    },
    {
      "ts": "2026-01-25T21:46:07.191118+00:00",
      "value": 0.825,
      "cash": 0.825
    },
    {
      "ts": "2026-01-25T21:57:20.501604+00:00",
      "value": 0.825,
      "cash": 0.825
    },
    {
      "ts": "2026-01-25T22:27:42.991922+00:00",
      "value": 0.825,
      "cash": 0.825
    },
    {
      "ts": "2026-01-25T22:47:33.545328+00:00",
      "value": 0.825,
      "cash": 0.825
    },
    {
      "ts": "2026-01-25T22:58:57.079984+00:00",
      "value": 0.825,
      "cash": 0.825
    },
    {
      "ts": "2026-01-25T23:29:05.597582+00:00",
      "value": 0.825,
      "cash": 0.825
    }
  ]
}