{
  "generated_at": "2026-01-18T07:21:54.459953+00:00",
  "prices_used": {},
  "selected_algorithm": "Event-Driven Strategies",
  "algorithm_leaderboard": [],
  "winner_target_allocations": {},
  "winner_top_coin_scores": [],
  "main": {
    "value": 0.825,
    "cash": 0.825,
    "holdings": {},
    "pnl": -999.175,
    "pnl_pct": -99.9175,
    "total_trades": 3,
    "tax_paid": 1.994361
  },
  "actions_this_run": [],
  "equity_history": [
    {
      "ts": "2026-01-18T03:58:43.474228+00:00",
      "value": 0.825,
      "cash": 0.825
    },
    {
      "ts": "2026-01-18T04:48:49.054737+00:00",
      "value": 0.825,
      "cash": 0.825
    },
    {
      "ts": "2026-01-18T05:13:24.862807+00:00",
      "value": 0.825,
      "cash": 0.825
    },
    {
      "ts": "2026-01-18T05:41:16.557959+00:00",
      "value": 0.825,
      "cash": 0.825
    },
    {
      "ts": "2026-01-18T05:54:14.536726+00:00",
      "value": 0.825,
      "cash": 0.825
    },
    {
      "ts": "2026-01-18T06:29:58.598482+00:00",
      "value": 0.825,
      "cash": 0.825
    },
    {
      "ts": "2026-01-18T06:55:30.700876+00:00",
      "value": 0.825,
      "cash": 0.825
    },
    {
      "ts": "2026-01-18T07:21:54.459953+00:00",
      "value": 0.825,
      "cash": 0.825
    }
  ]
}