{
  "generated_at": "2025-12-12T09:42:35.395696+00:00",
  "period": {
    "start": "2025-12-12 09:33:38.745395+00:00",
    "end": "2025-12-12 09:42:35.240805+00:00",
    "hours": 24
  },
  "summary": {
    "starting_cash": 1000.0,
    "ending_value": 1000.0,
    "pnl": 0.0,
    "pnl_pct": 0.0,
    "num_trades": 0,
    "tax_paid": 0.0,
    "tax_percent": 0.2,
    "slippage_bps": 5.0
  },
  "equity_curve": [
    {
      "ts": "2025-12-12 09:33:38.745395+00:00",
      "value": 1000.0,
      "cash": 1000.0
    },
    {
      "ts": "2025-12-12 09:42:35.240805+00:00",
      "value": 1000.0,
      "cash": 1000.0
    }
  ],
  "trades": [],
  "latest_scores": [
    {
      "coin": "sol",
      "score": 0.11343658194189993,
      "details": {
        "strategies": {
          "Trend Following (Momentum)": {
            "w": 1.0,
            "score": 0.0,
            "details": {
              "mom": null
            }
          },
          "Mean Reversion": {
            "w": 0.7,
            "score": -0.0,
            "details": {
              "z": null
            }
          },
          "Statistical Arbitrage": {
            "w": 0.4,
            "score": -0.0,
            "details": {
              "ret_12": 0.0,
              "cross_mean": 0.0
            }
          },
          "Market Making": {
            "w": 0.3,
            "score": 0.8047247639172342,
            "details": {
              "spread": 0.0029195485984711356,
              "volume_src": 5553.4615677688
            }
          },
          "High-Frequency Trading (HFT)": {
            "w": 0.3,
            "score": 0.01901035202733148,
            "details": {
              "ret_1step": 0.0027157645753330684,
              "ret_3step": 0.0
            }
          },
          "Machine Learning / AI-Based Strategies": {
            "w": 0.4,
            "score": 0.0,
            "details": {
              "note": "not_enough_data"
            }
          },
          "Event-Driven Strategies": {
            "w": 0.2,
            "score": 0.1458,
            "details": {
              "day_change_percent": 4.86
            }
          },
          "Execution Algorithms (VWAP, TWAP, POV, IS)": {
            "w": 0.0,
            "score": 0.0,
            "details": {
              "note": "modeled_via_slippage_and_tax"
            }
          },
          "Multi-Factor / Factor Investing": {
            "w": 0.8,
            "score": 0.2714285714285714,
            "details": {
              "mom_6h": 0.0,
              "vol_rank": 0.5714285714285714,
              "volume_src": 5553.4615677688
            }
          },
          "Volatility Arbitrage": {
            "w": 0.4,
            "score": 0.0,
            "details": {
              "vol_12": 0.0,
              "vol_72": 0.0,
              "z": 0.0
            }
          },
          "Cross-Exchange Arbitrage (Crypto)": {
            "w": 0.1,
            "score": 0.0,
            "details": {
              "note": "no_external_exchange_price_in_stats"
            }
          },
          "Liquidity Provision Bots (Crypto)": {
            "w": 0.2,
            "score": 0.563307334742064,
            "details": {
              "based_on": "spread_and_volume",
              "spread": 0.0029195485984711356,
              "volume_src": 5553.4615677688
            }
          },
          "Pairs Trading": {
            "w": 0.4,
            "score": 0.0,
            "details": {
              "note": "not_enough_data"
            }
          },
          "Basket Trading": {
            "w": 0.0,
            "score": 0.0,
            "details": {
              "note": "basket_is_allocation_method"
            }
          },
          "Reinforcement Learning Trading": {
            "w": 0.2,
            "score": 0.0,
            "details": {
              "note": "not_enough_data"
            }
          },
          "Sentiment/NLP-Based Trading": {
            "w": 0.2,
            "score": 0.1458,
            "details": {
              "day_change_percent": 4.86
            }
          },
          "Merger Arbitrage (Event-Driven subtype)": {
            "w": 0.0,
            "score": 0.0,
            "details": {
              "note": "not_applicable_in_crypto_stats"
            }
          }
        }
      }
    },
    {
      "coin": "eth",
      "score": 0.11004269019369514,
      "details": {
        "strategies": {
          "Trend Following (Momentum)": {
            "w": 1.0,
            "score": 0.0,
            "details": {
              "mom": null
            }
          },
          "Mean Reversion": {
            "w": 0.7,
            "score": -0.0,
            "details": {
              "z": null
            }
          },
          "Statistical Arbitrage": {
            "w": 0.4,
            "score": -0.0,
            "details": {
              "ret_12": 0.0,
              "cross_mean": 0.0
            }
          },
          "Market Making": {
            "w": 0.3,
            "score": 0.8753727429620416,
            "details": {
              "spread": 0.0002532419603398889,
              "volume_src": 316.4571347788
            }
          },
          "High-Frequency Trading (HFT)": {
            "w": 0.3,
            "score": -0.003910711088887298,
            "details": {
              "ret_1step": -0.0005586730126981854,
              "ret_3step": 0.0
            }
          },
          "Machine Learning / AI-Based Strategies": {
            "w": 0.4,
            "score": 0.0,
            "details": {
              "note": "not_enough_data"
            }
          },
          "Event-Driven Strategies": {
            "w": 0.2,
            "score": 0.0399,
            "details": {
              "day_change_percent": 1.33
            }
          },
          "Execution Algorithms (VWAP, TWAP, POV, IS)": {
            "w": 0.0,
            "score": 0.0,
            "details": {
              "note": "modeled_via_slippage_and_tax"
            }
          },
          "Multi-Factor / Factor Investing": {
            "w": 0.8,
            "score": 0.27036033938507603,
            "details": {
              "mom_6h": 0.0,
              "vol_rank": 0.5714285714285714,
              "volume_src": 316.4571347788
            }
          },
          "Volatility Arbitrage": {
            "w": 0.4,
            "score": 0.0,
            "details": {
              "vol_12": 0.0,
              "vol_72": 0.0,
              "z": 0.0
            }
          },
          "Cross-Exchange Arbitrage (Crypto)": {
            "w": 0.1,
            "score": 0.0,
            "details": {
              "note": "no_external_exchange_price_in_stats"
            }
          },
          "Liquidity Provision Bots (Crypto)": {
            "w": 0.2,
            "score": 0.6127609200734291,
            "details": {
              "based_on": "spread_and_volume",
              "spread": 0.0002532419603398889,
              "volume_src": 316.4571347788
            }
          },
          "Pairs Trading": {
            "w": 0.4,
            "score": 0.0,
            "details": {
              "note": "not_enough_data"
            }
          },
          "Basket Trading": {
            "w": 0.0,
            "score": 0.0,
            "details": {
              "note": "basket_is_allocation_method"
            }
          },
          "Reinforcement Learning Trading": {
            "w": 0.2,
            "score": 0.0,
            "details": {
              "note": "not_enough_data"
            }
          },
          "Sentiment/NLP-Based Trading": {
            "w": 0.2,
            "score": 0.0399,
            "details": {
              "day_change_percent": 1.33
            }
          },
          "Merger Arbitrage (Event-Driven subtype)": {
            "w": 0.0,
            "score": 0.0,
            "details": {
              "note": "not_applicable_in_crypto_stats"
            }
          }
        }
      }
    },
    {
      "coin": "ton",
      "score": 0.10797324176859877,
      "details": {
        "strategies": {
          "Trend Following (Momentum)": {
            "w": 1.0,
            "score": 0.0,
            "details": {
              "mom": null
            }
          },
          "Mean Reversion": {
            "w": 0.7,
            "score": -0.0,
            "details": {
              "z": null
            }
          },
          "Statistical Arbitrage": {
            "w": 0.4,
            "score": -0.0,
            "details": {
              "ret_12": 0.0,
              "cross_mean": 0.0
            }
          },
          "Market Making": {
            "w": 0.3,
            "score": 0.8362438562756727,
            "details": {
              "spread": 0.0018472906403941586,
              "volume_src": 20834.3910348934
            }
          },
          "High-Frequency Trading (HFT)": {
            "w": 0.3,
            "score": 0.0,
            "details": {
              "ret_1step": 0.0,
              "ret_3step": 0.0
            }
          },
          "Machine Learning / AI-Based Strategies": {
            "w": 0.4,
            "score": 0.0,
            "details": {
              "note": "not_enough_data"
            }
          },
          "Event-Driven Strategies": {
            "w": 0.2,
            "score": 0.04889999999999999,
            "details": {
              "day_change_percent": 1.63
            }
          },
          "Execution Algorithms (VWAP, TWAP, POV, IS)": {
            "w": 0.0,
            "score": 0.0,
            "details": {
              "note": "modeled_via_slippage_and_tax"
            }
          },
          "Multi-Factor / Factor Investing": {
            "w": 0.8,
            "score": 0.2714285714285714,
            "details": {
              "mom_6h": 0.0,
              "vol_rank": 0.5714285714285714,
              "volume_src": 20834.3910348934
            }
          },
          "Volatility Arbitrage": {
            "w": 0.4,
            "score": 0.0,
            "details": {
              "vol_12": 0.0,
              "vol_72": 0.0,
              "z": 0.0
            }
          },
          "Cross-Exchange Arbitrage (Crypto)": {
            "w": 0.1,
            "score": 0.0,
            "details": {
              "note": "no_external_exchange_price_in_stats"
            }
          },
          "Liquidity Provision Bots (Crypto)": {
            "w": 0.2,
            "score": 0.5853706993929708,
            "details": {
              "based_on": "spread_and_volume",
              "spread": 0.0018472906403941586,
              "volume_src": 20834.3910348934
            }
          },
          "Pairs Trading": {
            "w": 0.4,
            "score": 0.0,
            "details": {
              "note": "not_enough_data"
            }
          },
          "Basket Trading": {
            "w": 0.0,
            "score": 0.0,
            "details": {
              "note": "basket_is_allocation_method"
            }
          },
          "Reinforcement Learning Trading": {
            "w": 0.2,
            "score": 0.0,
            "details": {
              "note": "not_enough_data"
            }
          },
          "Sentiment/NLP-Based Trading": {
            "w": 0.2,
            "score": 0.04889999999999999,
            "details": {
              "day_change_percent": 1.63
            }
          },
          "Merger Arbitrage (Event-Driven subtype)": {
            "w": 0.0,
            "score": 0.0,
            "details": {
              "note": "not_applicable_in_crypto_stats"
            }
          }
        }
      }
    },
    {
      "coin": "doge",
      "score": 0.10621088342459584,
      "details": {
        "strategies": {
          "Trend Following (Momentum)": {
            "w": 1.0,
            "score": 0.0,
            "details": {
              "mom": null
            }
          },
          "Mean Reversion": {
            "w": 0.7,
            "score": -0.0,
            "details": {
              "z": null
            }
          },
          "Statistical Arbitrage": {
            "w": 0.4,
            "score": -0.0,
            "details": {
              "ret_12": 0.0,
              "cross_mean": 0.0
            }
          },
          "Market Making": {
            "w": 0.3,
            "score": 0.8288289740020209,
            "details": {
              "spread": 0.0021132468942268714,
              "volume_src": 1793421.302146342
            }
          },
          "High-Frequency Trading (HFT)": {
            "w": 0.3,
            "score": -0.0212221950866982,
            "details": {
              "ret_1step": -0.0030317421552426005,
              "ret_3step": 0.0
            }
          },
          "Machine Learning / AI-Based Strategies": {
            "w": 0.4,
            "score": 0.0,
            "details": {
              "note": "not_enough_data"
            }
          },
          "Event-Driven Strategies": {
            "w": 0.2,
            "score": 0.0483,
            "details": {
              "day_change_percent": 1.61
            }
          },
          "Execution Algorithms (VWAP, TWAP, POV, IS)": {
            "w": 0.0,
            "score": 0.0,
            "details": {
              "note": "modeled_via_slippage_and_tax"
            }
          },
          "Multi-Factor / Factor Investing": {
            "w": 0.8,
            "score": 0.2714285714285714,
            "details": {
              "mom_6h": 0.0,
              "vol_rank": 0.5714285714285714,
              "volume_src": 1793421.302146342
            }
          },
          "Volatility Arbitrage": {
            "w": 0.4,
            "score": 0.0,
            "details": {
              "vol_12": 0.0,
              "vol_72": 0.0,
              "z": 0.0
            }
          },
          "Cross-Exchange Arbitrage (Crypto)": {
            "w": 0.1,
            "score": 0.0,
            "details": {
              "note": "no_external_exchange_price_in_stats"
            }
          },
          "Liquidity Provision Bots (Crypto)": {
            "w": 0.2,
            "score": 0.5801802818014146,
            "details": {
              "based_on": "spread_and_volume",
              "spread": 0.0021132468942268714,
              "volume_src": 1793421.302146342
            }
          },
          "Pairs Trading": {
            "w": 0.4,
            "score": 0.0,
            "details": {
              "note": "not_enough_data"
            }
          },
          "Basket Trading": {
            "w": 0.0,
            "score": 0.0,
            "details": {
              "note": "basket_is_allocation_method"
            }
          },
          "Reinforcement Learning Trading": {
            "w": 0.2,
            "score": 0.0,
            "details": {
              "note": "not_enough_data"
            }
          },
          "Sentiment/NLP-Based Trading": {
            "w": 0.2,
            "score": 0.0483,
            "details": {
              "day_change_percent": 1.61
            }
          },
          "Merger Arbitrage (Event-Driven subtype)": {
            "w": 0.0,
            "score": 0.0,
            "details": {
              "note": "not_applicable_in_crypto_stats"
            }
          }
        }
      }
    },
    {
      "coin": "xrp",
      "score": 0.10502598303155355,
      "details": {
        "strategies": {
          "Trend Following (Momentum)": {
            "w": 1.0,
            "score": 0.0,
            "details": {
              "mom": null
            }
          },
          "Mean Reversion": {
            "w": 0.7,
            "score": -0.0,
            "details": {
              "z": null
            }
          },
          "Statistical Arbitrage": {
            "w": 0.4,
            "score": -0.0,
            "details": {
              "ret_12": 0.0,
              "cross_mean": 0.0
            }
          },
          "Market Making": {
            "w": 0.3,
            "score": 0.8278042468722872,
            "details": {
              "spread": 0.002149276098176636,
              "volume_src": 165377.9244543501
            }
          },
          "High-Frequency Trading (HFT)": {
            "w": 0.3,
            "score": -0.008237402633211599,
            "details": {
              "ret_1step": -0.0011767718047445141,
              "ret_3step": 0.0
            }
          },
          "Machine Learning / AI-Based Strategies": {
            "w": 0.4,
            "score": 0.0,
            "details": {
              "note": "not_enough_data"
            }
          },
          "Event-Driven Strategies": {
            "w": 0.2,
            "score": 0.0231,
            "details": {
              "day_change_percent": 0.77
            }
          },
          "Execution Algorithms (VWAP, TWAP, POV, IS)": {
            "w": 0.0,
            "score": 0.0,
            "details": {
              "note": "modeled_via_slippage_and_tax"
            }
          },
          "Multi-Factor / Factor Investing": {
            "w": 0.8,
            "score": 0.2714285714285714,
            "details": {
              "mom_6h": 0.0,
              "vol_rank": 0.5714285714285714,
              "volume_src": 165377.9244543501
            }
          },
          "Volatility Arbitrage": {
            "w": 0.4,
            "score": 0.0,
            "details": {
              "vol_12": 0.0,
              "vol_72": 0.0,
              "z": 0.0
            }
          },
          "Cross-Exchange Arbitrage (Crypto)": {
            "w": 0.1,
            "score": 0.0,
            "details": {
              "note": "no_external_exchange_price_in_stats"
            }
          },
          "Liquidity Provision Bots (Crypto)": {
            "w": 0.2,
            "score": 0.579462972810601,
            "details": {
              "based_on": "spread_and_volume",
              "spread": 0.002149276098176636,
              "volume_src": 165377.9244543501
            }
          },
          "Pairs Trading": {
            "w": 0.4,
            "score": 0.0,
            "details": {
              "note": "not_enough_data"
            }
          },
          "Basket Trading": {
            "w": 0.0,
            "score": 0.0,
            "details": {
              "note": "basket_is_allocation_method"
            }
          },
          "Reinforcement Learning Trading": {
            "w": 0.2,
            "score": 0.0,
            "details": {
              "note": "not_enough_data"
            }
          },
          "Sentiment/NLP-Based Trading": {
            "w": 0.2,
            "score": 0.0231,
            "details": {
              "day_change_percent": 0.77
            }
          },
          "Merger Arbitrage (Event-Driven subtype)": {
            "w": 0.0,
            "score": 0.0,
            "details": {
              "note": "not_applicable_in_crypto_stats"
            }
          }
        }
      }
    },
    {
      "coin": "ada",
      "score": 0.10158954448727642,
      "details": {
        "strategies": {
          "Trend Following (Momentum)": {
            "w": 1.0,
            "score": 0.0,
            "details": {
              "mom": null
            }
          },
          "Mean Reversion": {
            "w": 0.7,
            "score": -0.0,
            "details": {
              "z": null
            }
          },
          "Statistical Arbitrage": {
            "w": 0.4,
            "score": -0.0,
            "details": {
              "ret_12": 0.0,
              "cross_mean": 0.0
            }
          },
          "Market Making": {
            "w": 0.3,
            "score": 0.7996144248033209,
            "details": {
              "spread": 0.0030805687203792026,
              "volume_src": 594176.4380730484
            }
          },
          "High-Frequency Trading (HFT)": {
            "w": 0.3,
            "score": 0.014960816908098584,
            "details": {
              "ret_1step": 0.0021372595582997977,
              "ret_3step": 0.0
            }
          },
          "Machine Learning / AI-Based Strategies": {
            "w": 0.4,
            "score": 0.0,
            "details": {
              "note": "not_enough_data"
            }
          },
          "Event-Driven Strategies": {
            "w": 0.2,
            "score": -0.0114,
            "details": {
              "day_change_percent": -0.38
            }
          },
          "Execution Algorithms (VWAP, TWAP, POV, IS)": {
            "w": 0.0,
            "score": 0.0,
            "details": {
              "note": "modeled_via_slippage_and_tax"
            }
          },
          "Multi-Factor / Factor Investing": {
            "w": 0.8,
            "score": 0.2714285714285714,
            "details": {
              "mom_6h": 0.0,
              "vol_rank": 0.5714285714285714,
              "volume_src": 594176.4380730484
            }
          },
          "Volatility Arbitrage": {
            "w": 0.4,
            "score": 0.0,
            "details": {
              "vol_12": 0.0,
              "vol_72": 0.0,
              "z": 0.0
            }
          },
          "Cross-Exchange Arbitrage (Crypto)": {
            "w": 0.1,
            "score": 0.0,
            "details": {
              "note": "no_external_exchange_price_in_stats"
            }
          },
          "Liquidity Provision Bots (Crypto)": {
            "w": 0.2,
            "score": 0.5597300973623246,
            "details": {
              "based_on": "spread_and_volume",
              "spread": 0.0030805687203792026,
              "volume_src": 594176.4380730484
            }
          },
          "Pairs Trading": {
            "w": 0.4,
            "score": 0.0,
            "details": {
              "note": "not_enough_data"
            }
          },
          "Basket Trading": {
            "w": 0.0,
            "score": 0.0,
            "details": {
              "note": "basket_is_allocation_method"
            }
          },
          "Reinforcement Learning Trading": {
            "w": 0.2,
            "score": 0.0,
            "details": {
              "note": "not_enough_data"
            }
          },
          "Sentiment/NLP-Based Trading": {
            "w": 0.2,
            "score": -0.0114,
            "details": {
              "day_change_percent": -0.38
            }
          },
          "Merger Arbitrage (Event-Driven subtype)": {
            "w": 0.0,
            "score": 0.0,
            "details": {
              "note": "not_applicable_in_crypto_stats"
            }
          }
        }
      }
    },
    {
      "coin": "btc",
      "score": 0.04031330875371529,
      "details": {
        "strategies": {
          "Trend Following (Momentum)": {
            "w": 1.0,
            "score": 0.0,
            "details": {
              "mom": null
            }
          },
          "Mean Reversion": {
            "w": 0.7,
            "score": -0.0,
            "details": {
              "z": null
            }
          },
          "Statistical Arbitrage": {
            "w": 0.4,
            "score": -0.0,
            "details": {
              "ret_12": 0.0,
              "cross_mean": 0.0
            }
          },
          "Market Making": {
            "w": 0.3,
            "score": 0.4595259455106152,
            "details": {
              "spread": 0.0010978260869565217,
              "volume_src": 10.5305264179
            }
          },
          "High-Frequency Trading (HFT)": {
            "w": 0.3,
            "score": 0.0,
            "details": {
              "ret_1step": 0.0,
              "ret_3step": 0.0
            }
          },
          "Machine Learning / AI-Based Strategies": {
            "w": 0.4,
            "score": 0.0,
            "details": {
              "note": "not_enough_data"
            }
          },
          "Event-Driven Strategies": {
            "w": 0.2,
            "score": 0.0531,
            "details": {
              "day_change_percent": 1.77
            }
          },
          "Execution Algorithms (VWAP, TWAP, POV, IS)": {
            "w": 0.0,
            "score": 0.0,
            "details": {
              "note": "modeled_via_slippage_and_tax"
            }
          },
          "Multi-Factor / Factor Investing": {
            "w": 0.8,
            "score": 0.002903891245168752,
            "details": {
              "mom_6h": 0.0,
              "vol_rank": 0.5714285714285714,
              "volume_src": 10.5305264179
            }
          },
          "Volatility Arbitrage": {
            "w": 0.4,
            "score": 0.0,
            "details": {
              "vol_12": 0.0,
              "vol_72": 0.0,
              "z": 0.0
            }
          },
          "Cross-Exchange Arbitrage (Crypto)": {
            "w": 0.1,
            "score": 0.0,
            "details": {
              "note": "no_external_exchange_price_in_stats"
            }
          },
          "Liquidity Provision Bots (Crypto)": {
            "w": 0.2,
            "score": 0.32166816185743063,
            "details": {
              "based_on": "spread_and_volume",
              "spread": 0.0010978260869565217,
              "volume_src": 10.5305264179
            }
          },
          "Pairs Trading": {
            "w": 0.4,
            "score": 0.0,
            "details": {
              "note": "not_enough_data"
            }
          },
          "Basket Trading": {
            "w": 0.0,
            "score": 0.0,
            "details": {
              "note": "basket_is_allocation_method"
            }
          },
          "Reinforcement Learning Trading": {
            "w": 0.2,
            "score": 0.0,
            "details": {
              "note": "not_enough_data"
            }
          },
          "Sentiment/NLP-Based Trading": {
            "w": 0.2,
            "score": 0.0531,
            "details": {
              "day_change_percent": 1.77
            }
          },
          "Merger Arbitrage (Event-Driven subtype)": {
            "w": 0.0,
            "score": 0.0,
            "details": {
              "note": "not_applicable_in_crypto_stats"
            }
          }
        }
      }
    }
  ],
  "latest_allocations": {
    "cash": 1.0
  },
  "debug": {
    "holdings_qty": {}
  }
}